Metadata-Version: 2.1
Name: pipeline-sdk-test44
Version: 1.0.0
Summary: Multiple files in sigle sdk for pipeline execution.
Author: Saurav Kumar
Author-email: Saurav.Kumar@cognizant.com
Classifier: Programming Language :: Python :: 3
Classifier: License :: OSI Approved :: MIT License
Classifier: Operating System :: OS Independent
Requires-Python: >=3.6
